crypticorn/__init__.py
crypticorn/_internal/utils.py
crypticorn/_internal/warnings.py
crypticorn/auth/.openapi-generator/FILES
crypticorn/auth/.openapi-generator/VERSION
crypticorn/auth/.openapi-generator-ignore
crypticorn/auth/__init__.py
crypticorn/auth/client/__init__.py
crypticorn/auth/client/api/__init__.py
crypticorn/auth/client/api/admin_api.py
crypticorn/auth/client/api/auth_api.py
crypticorn/auth/client/api/user_api.py
crypticorn/auth/client/api/wallet_api.py
crypticorn/auth/client/api_client.py
crypticorn/auth/client/api_response.py
crypticorn/auth/client/configuration.py
crypticorn/auth/client/exceptions.py
crypticorn/auth/client/models/__init__.py
crypticorn/auth/client/models/add_wallet200_response.py
crypticorn/auth/client/models/add_wallet_request.py
crypticorn/auth/client/models/authorize_user200_response.py
crypticorn/auth/client/models/authorize_user_request.py
crypticorn/auth/client/models/create_api_key200_response.py
crypticorn/auth/client/models/create_api_key_request.py
crypticorn/auth/client/models/create_user200_response.py
crypticorn/auth/client/models/create_user200_response_auth.py
crypticorn/auth/client/models/create_user200_response_auth_auth.py
crypticorn/auth/client/models/create_user_request.py
crypticorn/auth/client/models/create_user_with_wallet_request.py
crypticorn/auth/client/models/error_badrequest.py
crypticorn/auth/client/models/error_forbidden.py
crypticorn/auth/client/models/error_internalservererror.py
crypticorn/auth/client/models/error_notfound.py
crypticorn/auth/client/models/error_unauthorized.py
crypticorn/auth/client/models/generate_otp_code_request.py
crypticorn/auth/client/models/get_api_keys200_response_inner.py
crypticorn/auth/client/models/get_license200_response.py
crypticorn/auth/client/models/link_license_request.py
crypticorn/auth/client/models/list_wallets200_response.py
crypticorn/auth/client/models/list_wallets200_response_data_inner.py
crypticorn/auth/client/models/refresh_token_info200_response.py
crypticorn-4.3.0.dist-info/licenses/LICENSE
crypticorn-4.3.0.dist-info/WHEEL
crypticorn-4.3.0.dist-info/METADATA
crypticorn-4.3.0.dist-info/RECORD
