Metadata-Version: 2.4
Name: crypticorn
Version: 4.3.0
Summary: Maximise Your Crypto Trading Profits with Machine Learning
Keywords: machine learning,data science,crypto,modelling
Author: Crypticorn
Author-email: Crypticorn <timon@crypticorn.com>
License-Expression: MIT
License-File: LICENSE
Classifier: Topic :: Scientific/Engineering
Classifier: Development Status :: 4 - Beta
Classifier: Intended Audience :: Developers
Classifier: Operating System :: OS Independent
Classifier: Programming Language :: Python :: 3.10
Classifier: Programming Language :: Python :: 3.11
Classifier: Programming Language :: Python :: 3.12
Classifier: Programming Language :: Python :: 3.13
Classifier: Programming Language :: Python :: 3.14
Classifier: Typing :: Typed
Requires-Dist: aiohttp>=3.8.4,<4.0.0
Requires-Dist: aiohttp-retry>=2.8.3,<3.0.0
Requires-Dist: asgiref>=3.6.0,<4.0.0
Requires-Dist: pydantic>=2.0.0,<3.0.0
Requires-Dist: python-dateutil>=2.8.2,<3.0.0
Requires-Dist: requests>=2.32.0,<3.0.0
Requires-Dist: tqdm>=4.67.0,<5.0.0
Requires-Dist: typing-extensions>=4.7.1,<5.0.0
Requires-Dist: urllib3>=1.25.3,<3.0.0
Requires-Dist: uv==0.9.17 ; extra == 'build'
Requires-Dist: pandas>=2.3.3 ; extra == 'extra'
Requires-Python: >=3.10
Project-URL: Changelog, https://github.com/crypticorn-ai/api-client-python/releases
Project-URL: Homepage, https://crypticorn.com
Provides-Extra: build
Provides-Extra: extra
